pycpu_retro/__init__.py
tests/__init__.py
tests/test_pycpu_retro.py
PyCPU_RETRO-0.0.11.dist-info/LICENSE.rst
PyCPU_RETRO-0.0.11.dist-info/METADATA
PyCPU_RETRO-0.0.11.dist-info/WHEEL
PyCPU_RETRO-0.0.11.dist-info/top_level.txt
PyCPU_RETRO-0.0.11.dist-info/RECORD
