Metadata-Version: 2.1
Name: PyCPU-RETRO
Version: 0.0.11
Summary: Dispatcher for the RETROFORTH CPU Type
Home-page: https://github.com/PyCPU/PyCPU_RETRO
Author: Scott McCallum (https github.com scott91e1) << Charles Childers (https github.com crcx)
Author-email: 262464@195387.com
License: UNKNOWN
Platform: UNKNOWN
Classifier: Programming Language :: Python :: 3
Classifier: License :: OSI Approved :: MIT License
Classifier: Operating System :: OS Independent
Requires-Python: >=3.6
